{"generated_at": "2026-06-28T13:13:03Z", "home": {"name": "哥倫比亞", "short_name": "哥倫比亞", "code": "COL", "confederation": "CONMEBOL", "fifa_ranking": 11, "elo_rating": 2117, "spi_rating": 83.0, "squad_value_m": 550, "avg_age": 26.8, "squad_depth": 7.5, "bench_quality": 7.2, "wc_titles": 0, "wc_best_result": "Fourth Place", "wc_appearances": 6, "coach": "Nestor Lorenzo", "coach_rating": 7.5, "attack": {"goals_per_game": 1.69, "xg_per_game": 1.62, "npxg_per_game": 1.53, "shots_per_game": 13.13, "shots_on_target_per_game": 4.699, "shots_in_box_per_game": 8.009, "big_chances_per_game": 2.258, "conversion_rate": 12.9, "counter_goals_pct": 19.43, "set_piece_goals_pct": 31.84, "corners_per_game": 5.755, "cross_accuracy_pct": 31.876, "key_passes_per_game": 3.853, "possession_pct": 55.641, "pass_accuracy_pct": 84.083}, "defense": {"goals_against_per_game": 0.89, "xga_per_game": 0.92, "clean_sheet_pct": 39.473, "shots_against_per_game": 10.824, "sot_against_per_game": 4.001, "tackle_success_pct": 68.095, "interceptions_per_game": 7.547, "clearances_per_game": 16.053, "aerial_success_pct": 60.837, "gk_save_pct": 71.814, "gk_psxg_ga": 0.126}, "advanced": {"ppda": 9.833, "field_tilt": 52.996, "deep_completion_per_game": 5.249, "progressive_passes": 57.482, "progressive_carries": 25.061, "shot_creating_actions": 16.137, "goal_creating_actions": 2.542, "xpts_per_game": 1.818}, "tactics": {"primary_formation": "4-2-3-1", "secondary_formation": "4-3-3", "possession_style": true, "high_press": true, "press_intensity": 8.0, "defensive_line": "medium", "wide_play_pct": 33.38, "set_piece_quality": 7.9, "tactical_flexibility": 7.9}, "key_players": [{"name": "Luis Diaz", "position": "FWD", "club": "Liverpool", "age": 27, "market_value_m": 90, "goals_season": 18, "assists_season": 8, "form_rating": 8.8, "is_injured": false, "is_suspended": false, "injury_detail": ""}, {"name": "James Rodriguez", "position": "MID", "club": "Rayo Vallecano", "age": 33, "market_value_m": 18, "goals_season": 7, "assists_season": 14, "form_rating": 8.2, "is_injured": false, "is_suspended": false, "injury_detail": ""}, {"name": "Jhon Duran", "position": "FWD", "club": "Aston Villa", "age": 21, "market_value_m": 55, "goals_season": 12, "assists_season": 5, "form_rating": 8.4, "is_injured": false, "is_suspended": false, "injury_detail": ""}, {"name": "Davinson Sanchez", "position": "DEF", "club": "Galatasaray", "age": 28, "market_value_m": 22, "goals_season": 2, "assists_season": 2, "form_rating": 7.8, "is_injured": false, "is_suspended": false, "injury_detail": ""}], "injured_players": [], "suspended_players": [], "recent_form": [], "form_pts_5": 1.5, "form_pts_10": 1.5, "win_rate_10": 33.0, "goals_scored_10": 1.69, "goals_conceded_10": 0.89}, "away": {"name": "蘇格蘭", "short_name": "蘇格蘭", "code": "SCO", "confederation": "UEFA", "fifa_ranking": 34, "elo_rating": 1683, "spi_rating": 71.5, "squad_value_m": 180, "avg_age": 27.5, "squad_depth": 6.3, "bench_quality": 6.0, "wc_titles": 0, "wc_best_result": "Group Stage", "wc_appearances": 10, "coach": "Steve Clarke", "coach_rating": 7.0, "attack": {"goals_per_game": 0.92, "xg_per_game": 0.89, "npxg_per_game": 0.94, "shots_per_game": 11.2, "shots_on_target_per_game": 4.102, "shots_in_box_per_game": 6.89, "big_chances_per_game": 1.796, "conversion_rate": 11.6, "counter_goals_pct": 33.83, "set_piece_goals_pct": 21.97, "corners_per_game": 5.204, "cross_accuracy_pct": 29.894, "key_passes_per_game": 3.242, "possession_pct": 52.501, "pass_accuracy_pct": 80.113}, "defense": {"goals_against_per_game": 1.38, "xga_per_game": 1.43, "clean_sheet_pct": 25.0, "shots_against_per_game": 12.577, "sot_against_per_game": 4.546, "tackle_success_pct": 67.007, "interceptions_per_game": 7.085, "clearances_per_game": 15.166, "aerial_success_pct": 54.206, "gk_save_pct": 70.669, "gk_psxg_ga": 0.07}, "advanced": {"ppda": 11.165, "field_tilt": 46.871, "deep_completion_per_game": 4.34, "progressive_passes": 49.784, "progressive_carries": 21.084, "shot_creating_actions": 13.758, "goal_creating_actions": 2.143, "xpts_per_game": 1.559}, "tactics": {"primary_formation": "3-5-2", "secondary_formation": "4-2-3-1", "possession_style": false, "high_press": true, "press_intensity": 6.8, "defensive_line": "medium", "wide_play_pct": 46.48, "set_piece_quality": 6.9, "tactical_flexibility": 6.9}, "key_players": [{"name": "Andrew Robertson", "position": "DEF", "club": "Liverpool", "age": 30, "market_value_m": 55, "goals_season": 2, "assists_season": 8, "form_rating": 8.8, "is_injured": false, "is_suspended": false, "injury_detail": ""}, {"name": "Scott McTominay", "position": "MID", "club": "Napoli", "age": 27, "market_value_m": 45, "goals_season": 8, "assists_season": 4, "form_rating": 8.2, "is_injured": false, "is_suspended": false, "injury_detail": ""}, {"name": "Kieran Tierney", "position": "DEF", "club": "Arsenal", "age": 27, "market_value_m": 30, "goals_season": 2, "assists_season": 4, "form_rating": 8.0, "is_injured": false, "is_suspended": false, "injury_detail": ""}, {"name": "John McGinn", "position": "MID", "club": "Aston Villa", "age": 30, "market_value_m": 28, "goals_season": 6, "assists_season": 7, "form_rating": 8.1, "is_injured": false, "is_suspended": false, "injury_detail": ""}], "injured_players": [], "suspended_players": [], "recent_form": [], "form_pts_5": 1.5, "form_pts_10": 1.5, "win_rate_10": 33.0, "goals_scored_10": 0.92, "goals_conceded_10": 1.38}, "result": {"p_home": 64.7, "p_draw": 26.4, "p_away": 9.0, "lambda_home": 2.24, "lambda_away": 0.66, "btts_yes": 44.8, "btts_no": 55.2, "score_matrix": [[7.44, 5.22, 2.15, 0.57, 0.11, 0.02], [12.85, 10.22, 3.87, 1.01, 0.2, 0.03], [12.34, 9.22, 3.52, 0.93, 0.18, 0.03], [7.95, 5.83, 2.22, 0.57, 0.11, 0.02], [3.97, 2.87, 1.07, 0.27, 0.05, 0.01], [1.66, 1.16, 0.43, 0.11, 0.02, 0.0]], "top10": [{"home": 1, "away": 0, "prob": 12.85, "type": "home"}, {"home": 2, "away": 0, "prob": 12.34, "type": "home"}, {"home": 1, "away": 1, "prob": 10.22, "type": "draw"}, {"home": 2, "away": 1, "prob": 9.22, "type": "home"}, {"home": 3, "away": 0, "prob": 7.95, "type": "home"}, {"home": 0, "away": 0, "prob": 7.44, "type": "draw"}, {"home": 3, "away": 1, "prob": 5.83, "type": "home"}, {"home": 0, "away": 1, "prob": 5.22, "type": "away"}, {"home": 4, "away": 0, "prob": 3.97, "type": "home"}, {"home": 1, "away": 2, "prob": 3.87, "type": "away"}], "goal_dist": [{"label": "0", "prob": 7.44}, {"label": "1", "prob": 18.07}, {"label": "2", "prob": 24.7}, {"label": "3", "prob": 21.6}, {"label": "4", "prob": 14.45}, {"label": "5", "prob": 7.9}, {"label": "6+", "prob": 5.83}], "cold": [{"home": 3, "away": 1, "prob": 5.83, "odds": 17.2}, {"home": 4, "away": 0, "prob": 3.97, "odds": 25.2}, {"home": 2, "away": 2, "prob": 3.52, "odds": 28.4}], "models": [{"name": "ELO", "p_home": 65.9, "p_draw": 21.9, "p_away": 12.3, "lam_home": 1.87, "lam_away": 0.82}, {"name": "Poisson", "p_home": 58.2, "p_draw": 23.8, "p_away": 18.0, "lam_home": 1.71, "lam_away": 0.83}, {"name": "Dixon-Coles", "p_home": 57.8, "p_draw": 24.7, "p_away": 17.5, "lam_home": 1.71, "lam_away": 0.83}, {"name": "xG Model", "p_home": 66.2, "p_draw": 20.4, "p_away": 13.4, "lam_home": 2.09, "lam_away": 0.83}, {"name": "Market", "p_home": 53.9, "p_draw": 24.4, "p_away": 21.7, "lam_home": 1.71, "lam_away": 1.01}, {"name": "ML", "p_home": 83.8, "p_draw": 14.1, "p_away": 2.1, "lam_home": 2.63, "lam_away": 0.3}, {"name": "Monte Carlo", "p_home": 72.6, "p_draw": 17.5, "p_away": 9.9, "lam_home": 2.24, "lam_away": 0.66}], "betting": {"home": {"odds": 1.98, "implied": 50.5, "model": 64.7, "edge": 14.2}, "draw": {"odds": 4.43, "implied": 22.6, "model": 26.4, "edge": 3.8}, "away": {"odds": 4.94, "implied": 20.2, "model": 9.0, "edge": -11.3}, "over": {"line": 2.5, "odds": 1.83, "implied": 54.6, "model": 49.8, "edge": -4.9}, "under": {"line": 2.5, "odds": 1.97, "implied": 50.8, "model": 50.2, "edge": -0.5}, "ah_line": -1.0, "ah_home_odds": 1.91, "ah_away_odds": 2.02, "btts": {"yes": 44.8, "no": 55.2}, "movement": {"open_home": null, "open_draw": null, "open_away": null, "home_drift": null, "away_drift": null, "ah_open": null, "ah_close": null, "ah_move": null, "sharp_index": 0.5, "signal": "neutral", "steam": false}}}, "conf_level": 9, "conf_label": "極高信心", "match": {"date": "2026-06-14", "venue": "MetLife Stadium, East Rutherford, NJ", "comp": "FIFA World Cup 2026", "stage": "Group Stage"}}