{"generated_at": "2026-06-28T14:29:40Z", "home": {"name": "法國", "short_name": "法國", "code": "FRA", "confederation": "UEFA", "fifa_ranking": 2, "elo_rating": 2328, "spi_rating": 92.1, "squad_value_m": 1350, "avg_age": 27.1, "squad_depth": 9.8, "bench_quality": 9.5, "wc_titles": 2, "wc_best_result": "Champion", "wc_appearances": 16, "coach": "Didier Deschamps", "coach_rating": 9.2, "attack": {"goals_per_game": 2.97, "xg_per_game": 2.85, "npxg_per_game": 1.9, "shots_per_game": 16.2, "shots_on_target_per_game": 6.1, "shots_in_box_per_game": 10.4, "big_chances_per_game": 3.2, "conversion_rate": 14.2, "counter_goals_pct": 30, "set_piece_goals_pct": 25, "corners_per_game": 6.8, "cross_accuracy_pct": 30, "key_passes_per_game": 4.3, "possession_pct": 54.8, "pass_accuracy_pct": 88.5}, "defense": {"goals_against_per_game": 0.92, "xga_per_game": 0.95, "clean_sheet_pct": 42, "shots_against_per_game": 8.2, "sot_against_per_game": 2.9, "tackle_success_pct": 74, "interceptions_per_game": 8.5, "clearances_per_game": 13.0, "aerial_success_pct": 65, "gk_save_pct": 76.5, "gk_psxg_ga": 0.22}, "advanced": {"ppda": 7.5, "field_tilt": 58.9, "deep_completion_per_game": 6.5, "progressive_passes": 65.2, "progressive_carries": 31.8, "shot_creating_actions": 20.1, "goal_creating_actions": 3.5, "xpts_per_game": 2.35}, "tactics": {"primary_formation": "4-3-3", "secondary_formation": "4-2-3-1", "possession_style": false, "high_press": true, "press_intensity": 8.2, "defensive_line": "high", "wide_play_pct": 45, "set_piece_quality": 8.0, "tactical_flexibility": 9.0}, "key_players": [{"name": "Kylian Mbappé", "position": "FWD", "club": "Real Madrid", "age": 27, "market_value_m": 180, "goals_season": 32, "assists_season": 16, "form_rating": 9.3, "is_injured": false, "is_suspended": false, "injury_detail": ""}, {"name": "Antoine Griezmann", "position": "MID", "club": "Atlético Madrid", "age": 35, "market_value_m": 20, "goals_season": 14, "assists_season": 11, "form_rating": 8.2, "is_injured": false, "is_suspended": false, "injury_detail": ""}, {"name": "Aurélien Tchouaméni", "position": "MID", "club": "Real Madrid", "age": 24, "market_value_m": 100, "goals_season": 3, "assists_season": 5, "form_rating": 8.5, "is_injured": false, "is_suspended": false, "injury_detail": ""}, {"name": "William Saliba", "position": "DEF", "club": "Arsenal", "age": 23, "market_value_m": 100, "goals_season": 2, "assists_season": 3, "form_rating": 9.0, "is_injured": false, "is_suspended": false, "injury_detail": ""}, {"name": "Mike Maignan", "position": "GK", "club": "AC Milan", "age": 29, "market_value_m": 55, "goals_season": 0, "assists_season": 0, "form_rating": 8.8, "is_injured": false, "is_suspended": false, "injury_detail": ""}], "injured_players": [], "suspended_players": [], "recent_form": ["W", "W", "W", "W", "W", "W", "W", "W", "W", "W"], "form_pts_5": 3.0, "form_pts_10": 3.0, "win_rate_10": 100.0, "goals_scored_10": 2.6, "goals_conceded_10": 0.4}, "away": {"name": "摩洛哥", "short_name": "摩洛哥", "code": "MAR", "confederation": "CAF", "fifa_ranking": 14, "elo_rating": 2137, "spi_rating": 78.5, "squad_value_m": 380, "avg_age": 27.5, "squad_depth": 7.8, "bench_quality": 7.5, "wc_titles": 0, "wc_best_result": "4th Place", "wc_appearances": 6, "coach": "Walid Regragui", "coach_rating": 8.8, "attack": {"goals_per_game": 1.37, "xg_per_game": 1.31, "npxg_per_game": 1.3, "shots_per_game": 11.5, "shots_on_target_per_game": 4.0, "shots_in_box_per_game": 7.5, "big_chances_per_game": 2.0, "conversion_rate": 13.5, "counter_goals_pct": 40, "set_piece_goals_pct": 35, "corners_per_game": 5.2, "cross_accuracy_pct": 28, "key_passes_per_game": 3.0, "possession_pct": 46.5, "pass_accuracy_pct": 83.5}, "defense": {"goals_against_per_game": 0.77, "xga_per_game": 0.79, "clean_sheet_pct": 58, "shots_against_per_game": 9.8, "sot_against_per_game": 3.5, "tackle_success_pct": 75, "interceptions_per_game": 9.0, "clearances_per_game": 19.5, "aerial_success_pct": 70, "gk_save_pct": 78.5, "gk_psxg_ga": 0.28}, "advanced": {"ppda": 10.5, "field_tilt": 46.5, "deep_completion_per_game": 3.8, "progressive_passes": 44.5, "progressive_carries": 20.5, "shot_creating_actions": 14.5, "goal_creating_actions": 2.2, "xpts_per_game": 1.78}, "tactics": {"primary_formation": "4-4-2", "secondary_formation": "5-4-1", "possession_style": false, "high_press": true, "press_intensity": 8.5, "defensive_line": "low", "wide_play_pct": 42, "set_piece_quality": 8.0, "tactical_flexibility": 8.5}, "key_players": [{"name": "Achraf Hakimi", "position": "DEF", "club": "PSG", "age": 25, "market_value_m": 65, "goals_season": 5, "assists_season": 12, "form_rating": 9.0, "is_injured": false, "is_suspended": false, "injury_detail": ""}, {"name": "Hakim Ziyech", "position": "MID", "club": "Galatasaray", "age": 31, "market_value_m": 15, "goals_season": 12, "assists_season": 10, "form_rating": 8.0, "is_injured": false, "is_suspended": false, "injury_detail": ""}, {"name": "Youssef En-Nesyri", "position": "FWD", "club": "Fenerbahçe", "age": 27, "market_value_m": 30, "goals_season": 18, "assists_season": 6, "form_rating": 8.2, "is_injured": false, "is_suspended": false, "injury_detail": ""}, {"name": "Azzedine Ounahi", "position": "MID", "club": "Marseille", "age": 23, "market_value_m": 28, "goals_season": 5, "assists_season": 7, "form_rating": 8.2, "is_injured": false, "is_suspended": false, "injury_detail": ""}, {"name": "Yassine Bounou", "position": "GK", "club": "Al-Hilal", "age": 32, "market_value_m": 15, "goals_season": 0, "assists_season": 0, "form_rating": 8.8, "is_injured": false, "is_suspended": false, "injury_detail": ""}], "injured_players": [], "suspended_players": [], "recent_form": ["W", "L", "L", "W", "W", "W", "W", "W", "W", "W"], "form_pts_5": 3.0, "form_pts_10": 2.4, "win_rate_10": 80.0, "goals_scored_10": 1.9, "goals_conceded_10": 0.5}, "result": {"p_home": 51.5, "p_draw": 29.0, "p_away": 19.5, "lambda_home": 1.99, "lambda_away": 1.11, "btts_yes": 64.7, "btts_no": 35.3, "score_matrix": [[3.76, 4.49, 3.3, 1.6, 0.61, 0.19], [6.61, 9.33, 6.42, 3.15, 1.19, 0.37], [6.67, 8.94, 6.32, 3.11, 1.18, 0.37], [4.44, 5.95, 4.21, 2.07, 0.78, 0.24], [2.24, 2.99, 2.11, 1.03, 0.39, 0.12], [0.93, 1.22, 0.86, 0.42, 0.16, 0.05]], "top10": [{"home": 1, "away": 1, "prob": 9.33, "type": "draw"}, {"home": 2, "away": 1, "prob": 8.94, "type": "home"}, {"home": 2, "away": 0, "prob": 6.67, "type": "home"}, {"home": 1, "away": 0, "prob": 6.61, "type": "home"}, {"home": 1, "away": 2, "prob": 6.42, "type": "away"}, {"home": 2, "away": 2, "prob": 6.32, "type": "draw"}, {"home": 3, "away": 1, "prob": 5.95, "type": "home"}, {"home": 0, "away": 1, "prob": 4.49, "type": "away"}, {"home": 3, "away": 0, "prob": 4.44, "type": "home"}, {"home": 3, "away": 2, "prob": 4.21, "type": "home"}], "goal_dist": [{"label": "0", "prob": 3.76}, {"label": "1", "prob": 11.1}, {"label": "2", "prob": 19.31}, {"label": "3", "prob": 21.4}, {"label": "4", "prob": 18.27}, {"label": "5", "prob": 12.62}, {"label": "6+", "prob": 13.56}], "cold": [{"home": 2, "away": 2, "prob": 6.32, "odds": 15.8}, {"home": 3, "away": 1, "prob": 5.95, "odds": 16.8}, {"home": 3, "away": 2, "prob": 4.21, "odds": 23.8}], "models": [{"name": "ELO", "p_home": 52.6, "p_draw": 24.8, "p_away": 22.6, "lam_home": 1.62, "lam_away": 0.95}, {"name": "Poisson", "p_home": 46.3, "p_draw": 21.5, "p_away": 32.1, "lam_home": 1.99, "lam_away": 1.63}, {"name": "Dixon-Coles", "p_home": 46.0, "p_draw": 22.2, "p_away": 31.8, "lam_home": 1.99, "lam_away": 1.63}, {"name": "xG Model", "p_home": 62.0, "p_draw": 18.3, "p_away": 19.6, "lam_home": 2.6, "lam_away": 1.45}, {"name": "Market", "p_home": 48.3, "p_draw": 28.1, "p_away": 23.7, "lam_home": 1.37, "lam_away": 0.89}, {"name": "ML", "p_home": 57.8, "p_draw": 15.7, "p_away": 26.5, "lam_home": 1.85, "lam_away": 0.85}, {"name": "Monte Carlo", "p_home": 57.3, "p_draw": 21.4, "p_away": 21.2, "lam_home": 1.99, "lam_away": 1.11}], "betting": {"home": {"odds": 1.95, "implied": 51.3, "model": 51.5, "edge": 0.2}, "draw": {"odds": 3.4, "implied": 29.4, "model": 29.0, "edge": -0.4}, "away": {"odds": 4.0, "implied": 25.0, "model": 19.5, "edge": -5.5}, "over": {"line": 2.5, "odds": 1.95, "implied": 51.3, "model": 65.8, "edge": 14.6}, "under": {"line": 2.5, "odds": 1.88, "implied": 53.2, "model": 34.2, "edge": -19.0}, "ah_line": -0.5, "ah_home_odds": 1.94, "ah_away_odds": 1.98, "btts": {"yes": 64.7, "no": 35.3}, "movement": {"open_home": null, "open_draw": null, "open_away": null, "home_drift": null, "away_drift": null, "ah_open": null, "ah_close": null, "ah_move": null, "sharp_index": 0.5, "signal": "neutral", "steam": false}}}, "conf_level": 7, "conf_label": "中高信心", "match": {"date": "2026-06-14", "venue": "MetLife Stadium, East Rutherford, NJ", "comp": "FIFA World Cup 2026", "stage": "Group Stage"}}