{"generated_at": "2026-06-27T08:27:02Z", "home": {"name": "日本", "short_name": "日本", "code": "JPN", "confederation": "AFC", "fifa_ranking": 16, "elo_rating": 2002, "spi_rating": 74.2, "squad_value_m": 360, "avg_age": 26.2, "squad_depth": 6.6, "bench_quality": 6.2, "wc_titles": 0, "wc_best_result": "Quarter-Final", "wc_appearances": 7, "coach": "Hajime Moriyasu", "coach_rating": 7.5, "attack": {"goals_per_game": 1.65, "xg_per_game": 1.59, "npxg_per_game": 1.23, "shots_per_game": 11.878, "shots_on_target_per_game": 4.03, "shots_in_box_per_game": 7.192, "big_chances_per_game": 1.818, "conversion_rate": 12.0, "counter_goals_pct": 24.44, "set_piece_goals_pct": 27.14, "corners_per_game": 5.148, "cross_accuracy_pct": 28.887, "key_passes_per_game": 3.445, "possession_pct": 53.463, "pass_accuracy_pct": 79.64}, "defense": {"goals_against_per_game": 1.12, "xga_per_game": 1.15, "clean_sheet_pct": 32.567, "shots_against_per_game": 12.065, "sot_against_per_game": 4.701, "tackle_success_pct": 66.236, "interceptions_per_game": 6.855, "clearances_per_game": 16.16, "aerial_success_pct": 57.389, "gk_save_pct": 72.536, "gk_psxg_ga": 0.084}, "advanced": {"ppda": 10.909, "field_tilt": 48.243, "deep_completion_per_game": 4.315, "progressive_passes": 52.472, "progressive_carries": 22.209, "shot_creating_actions": 15.126, "goal_creating_actions": 2.296, "xpts_per_game": 1.664}, "tactics": {"primary_formation": "4-2-3-1", "secondary_formation": "3-4-3", "possession_style": true, "high_press": true, "press_intensity": 7.1, "defensive_line": "high", "wide_play_pct": 35.16, "set_piece_quality": 7.1, "tactical_flexibility": 7.1}, "key_players": [{"name": "Takumi Minamino", "position": "FWD", "club": "Monaco", "age": 30, "market_value_m": 22, "goals_season": 10, "assists_season": 8, "form_rating": 8.0, "is_injured": false, "is_suspended": false, "injury_detail": ""}, {"name": "Ritsu Doan", "position": "FWD", "club": "Freiburg", "age": 26, "market_value_m": 30, "goals_season": 12, "assists_season": 7, "form_rating": 8.3, "is_injured": false, "is_suspended": false, "injury_detail": ""}, {"name": "Daichi Kamada", "position": "MID", "club": "Crystal Palace", "age": 28, "market_value_m": 22, "goals_season": 7, "assists_season": 8, "form_rating": 8.2, "is_injured": false, "is_suspended": false, "injury_detail": ""}, {"name": "Ko Itakura", "position": "DEF", "club": "Borussia M'gladbach", "age": 27, "market_value_m": 18, "goals_season": 1, "assists_season": 2, "form_rating": 8.0, "is_injured": false, "is_suspended": false, "injury_detail": ""}], "injured_players": [], "suspended_players": [], "recent_form": [], "form_pts_5": 1.5, "form_pts_10": 1.5, "win_rate_10": 33.0, "goals_scored_10": 1.65, "goals_conceded_10": 1.12}, "away": {"name": "澳洲", "short_name": "澳洲", "code": "AUS", "confederation": "AFC", "fifa_ranking": 23, "elo_rating": 1812, "spi_rating": 67.0, "squad_value_m": 180, "avg_age": 27.8, "squad_depth": 5.8, "bench_quality": 5.4, "wc_titles": 0, "wc_best_result": "Quarter-Final", "wc_appearances": 5, "coach": "Tony Popovic", "coach_rating": 7.0, "attack": {"goals_per_game": 0.95, "xg_per_game": 0.91, "npxg_per_game": 1.073, "shots_per_game": 9.987, "shots_on_target_per_game": 3.58, "shots_in_box_per_game": 6.078, "big_chances_per_game": 1.574, "conversion_rate": 11.0, "counter_goals_pct": 33.31, "set_piece_goals_pct": 22.43, "corners_per_game": 4.688, "cross_accuracy_pct": 28.692, "key_passes_per_game": 3.16, "possession_pct": 49.16, "pass_accuracy_pct": 79.372}, "defense": {"goals_against_per_game": 0.88, "xga_per_game": 0.91, "clean_sheet_pct": 25.479, "shots_against_per_game": 13.178, "sot_against_per_game": 4.847, "tackle_success_pct": 67.312, "interceptions_per_game": 6.463, "clearances_per_game": 15.265, "aerial_success_pct": 56.028, "gk_save_pct": 72.463, "gk_psxg_ga": 0.042}, "advanced": {"ppda": 12.081, "field_tilt": 44.021, "deep_completion_per_game": 3.796, "progressive_passes": 45.076, "progressive_carries": 19.933, "shot_creating_actions": 12.872, "goal_creating_actions": 1.997, "xpts_per_game": 1.344}, "tactics": {"primary_formation": "4-3-3", "secondary_formation": "4-4-2", "possession_style": false, "high_press": true, "press_intensity": 6.3, "defensive_line": "medium", "wide_play_pct": 39.12, "set_piece_quality": 6.5, "tactical_flexibility": 6.5}, "key_players": [{"name": "Mathew Leckie", "position": "FWD", "club": "Melbourne City", "age": 34, "market_value_m": 5, "goals_season": 8, "assists_season": 5, "form_rating": 7.8, "is_injured": false, "is_suspended": false, "injury_detail": ""}, {"name": "Mat Ryan", "position": "GK", "club": "Copenhagen", "age": 32, "market_value_m": 8, "goals_season": 0, "assists_season": 0, "form_rating": 7.8, "is_injured": false, "is_suspended": false, "injury_detail": ""}, {"name": "Cameron Devlin", "position": "MID", "club": "Hearts", "age": 26, "market_value_m": 6, "goals_season": 3, "assists_season": 5, "form_rating": 7.5, "is_injured": false, "is_suspended": false, "injury_detail": ""}, {"name": "Harry Souttar", "position": "DEF", "club": "Leicester", "age": 26, "market_value_m": 12, "goals_season": 2, "assists_season": 2, "form_rating": 7.6, "is_injured": false, "is_suspended": false, "injury_detail": ""}], "injured_players": [], "suspended_players": [], "recent_form": [], "form_pts_5": 1.5, "form_pts_10": 1.5, "win_rate_10": 33.0, "goals_scored_10": 0.95, "goals_conceded_10": 0.88}, "result": {"p_home": 52.3, "p_draw": 29.3, "p_away": 18.4, "lambda_home": 1.73, "lambda_away": 0.88, "btts_yes": 46.1, "btts_no": 53.9, "score_matrix": [[9.75, 8.52, 4.19, 1.34, 0.32, 0.06], [12.82, 12.54, 5.78, 1.84, 0.44, 0.09], [9.46, 8.69, 4.08, 1.29, 0.32, 0.06], [4.71, 4.29, 1.99, 0.63, 0.15, 0.03], [1.83, 1.64, 0.77, 0.24, 0.06, 0.01], [0.6, 0.53, 0.25, 0.07, 0.02, 0.0]], "top10": [{"home": 1, "away": 0, "prob": 12.82, "type": "home"}, {"home": 1, "away": 1, "prob": 12.54, "type": "draw"}, {"home": 0, "away": 0, "prob": 9.75, "type": "draw"}, {"home": 2, "away": 0, "prob": 9.46, "type": "home"}, {"home": 2, "away": 1, "prob": 8.69, "type": "home"}, {"home": 0, "away": 1, "prob": 8.52, "type": "away"}, {"home": 1, "away": 2, "prob": 5.78, "type": "away"}, {"home": 3, "away": 0, "prob": 4.71, "type": "home"}, {"home": 3, "away": 1, "prob": 4.29, "type": "home"}, {"home": 0, "away": 2, "prob": 4.19, "type": "away"}], "goal_dist": [{"label": "0", "prob": 9.75}, {"label": "1", "prob": 21.34}, {"label": "2", "prob": 26.18}, {"label": "3", "prob": 20.52}, {"label": "4", "prob": 12.35}, {"label": "5", "prob": 6.02}, {"label": "6+", "prob": 3.82}], "cold": [{"home": 3, "away": 1, "prob": 4.29, "odds": 23.3}, {"home": 2, "away": 2, "prob": 4.08, "odds": 24.5}, {"home": 3, "away": 2, "prob": 1.99, "odds": 50.4}], "models": [{"name": "ELO", "p_home": 51.0, "p_draw": 25.1, "p_away": 24.0, "lam_home": 1.6, "lam_away": 0.96}, {"name": "Poisson", "p_home": 43.1, "p_draw": 28.3, "p_away": 28.6, "lam_home": 1.27, "lam_away": 0.98}, {"name": "Dixon-Coles", "p_home": 42.6, "p_draw": 29.4, "p_away": 28.0, "lam_home": 1.27, "lam_away": 0.98}, {"name": "xG Model", "p_home": 50.9, "p_draw": 26.4, "p_away": 22.6, "lam_home": 1.56, "lam_away": 0.95}, {"name": "Market", "p_home": 48.8, "p_draw": 25.4, "p_away": 25.8, "lam_home": 1.6, "lam_away": 1.11}, {"name": "ML", "p_home": 69.9, "p_draw": 14.2, "p_away": 15.9, "lam_home": 2.2, "lam_away": 0.5}, {"name": "Monte Carlo", "p_home": 57.2, "p_draw": 23.6, "p_away": 19.2, "lam_home": 1.73, "lam_away": 0.88}], "betting": {"home": {"odds": 2.18, "implied": 45.9, "model": 52.3, "edge": 6.5}, "draw": {"odds": 4.25, "implied": 23.5, "model": 29.3, "edge": 5.7}, "away": {"odds": 4.15, "implied": 24.1, "model": 18.4, "edge": -5.7}, "over": {"line": 2.5, "odds": 1.79, "implied": 55.9, "model": 42.7, "edge": -13.1}, "under": {"line": 2.5, "odds": 2.01, "implied": 49.8, "model": 57.3, "edge": 7.5}, "ah_line": -0.5, "ah_home_odds": 2.02, "ah_away_odds": 1.9, "btts": {"yes": 46.1, "no": 53.9}, "movement": {"open_home": null, "open_draw": null, "open_away": null, "home_drift": null, "away_drift": null, "ah_open": null, "ah_close": null, "ah_move": null, "sharp_index": 0.5, "signal": "neutral", "steam": false}}}, "conf_level": 7, "conf_label": "中高信心", "match": {"date": "2026-06-14", "venue": "MetLife Stadium, East Rutherford, NJ", "comp": "FIFA World Cup 2026", "stage": "Group Stage"}}