{"generated_at": "2026-06-20T17:39:26Z", "home": {"name": "巴拿馬", "short_name": "巴拿馬", "code": "PAN", "confederation": "CONCACAF", "fifa_ranking": 81, "elo_rating": 1647, "spi_rating": 62.0, "squad_value_m": 35, "avg_age": 29.5, "squad_depth": 5.1, "bench_quality": 4.7, "wc_titles": 0, "wc_best_result": "Group Stage", "wc_appearances": 2, "coach": "Thomas Christiansen", "coach_rating": 6.5, "attack": {"goals_per_game": 0.8, "xg_per_game": 0.82, "npxg_per_game": 0.855, "shots_per_game": 9.133, "shots_on_target_per_game": 3.19, "shots_in_box_per_game": 5.547, "big_chances_per_game": 1.196, "conversion_rate": 10.4, "counter_goals_pct": 24.55, "set_piece_goals_pct": 36.72, "corners_per_game": 4.26, "cross_accuracy_pct": 26.134, "key_passes_per_game": 2.704, "possession_pct": 46.684, "pass_accuracy_pct": 76.912}, "defense": {"goals_against_per_game": 1.11, "xga_per_game": 1.14, "clean_sheet_pct": 19.943, "shots_against_per_game": 13.953, "sot_against_per_game": 5.291, "tackle_success_pct": 64.022, "interceptions_per_game": 6.177, "clearances_per_game": 14.391, "aerial_success_pct": 54.768, "gk_save_pct": 70.502, "gk_psxg_ga": 0.006}, "advanced": {"ppda": 12.904, "field_tilt": 42.834, "deep_completion_per_game": 3.409, "progressive_passes": 41.498, "progressive_carries": 17.178, "shot_creating_actions": 11.797, "goal_creating_actions": 1.634, "xpts_per_game": 1.193}, "tactics": {"primary_formation": "4-4-2", "secondary_formation": "5-4-1", "possession_style": false, "high_press": false, "press_intensity": 5.6, "defensive_line": "low", "wide_play_pct": 57.67, "set_piece_quality": 5.9, "tactical_flexibility": 5.9}, "key_players": [{"name": "Rolando Blackburn", "position": "FWD", "club": "Club Atletico Independiente", "age": 27, "market_value_m": 3, "goals_season": 6, "assists_season": 3, "form_rating": 7.5, "is_injured": false, "is_suspended": false, "injury_detail": ""}, {"name": "Jose Fajardo", "position": "FWD", "club": "Al-Qadsiah", "age": 24, "market_value_m": 8, "goals_season": 5, "assists_season": 4, "form_rating": 7.6, "is_injured": false, "is_suspended": false, "injury_detail": ""}, {"name": "Ricardo Avila", "position": "MID", "club": "New York City FC", "age": 28, "market_value_m": 4, "goals_season": 2, "assists_season": 5, "form_rating": 7.4, "is_injured": false, "is_suspended": false, "injury_detail": ""}, {"name": "Eric Davis", "position": "DEF", "club": "New York Red Bulls", "age": 34, "market_value_m": 2, "goals_season": 1, "assists_season": 1, "form_rating": 7.2, "is_injured": false, "is_suspended": false, "injury_detail": ""}], "injured_players": [], "suspended_players": [], "recent_form": ["W", "L", "L", "D", "W", "W", "D", "W", "D", "W"], "form_pts_5": 2.2, "form_pts_10": 1.8, "win_rate_10": 50.0, "goals_scored_10": 1.8, "goals_conceded_10": 1.0}, "away": {"name": "巴西", "short_name": "巴西", "code": "BRA", "confederation": "CONMEBOL", "fifa_ranking": 3, "elo_rating": 1980, "spi_rating": 90.5, "squad_value_m": 1150, "avg_age": 26.2, "squad_depth": 9.5, "bench_quality": 9.2, "wc_titles": 5, "wc_best_result": "Champion", "wc_appearances": 22, "coach": "Fernando Diniz", "coach_rating": 8.0, "attack": {"goals_per_game": 1.77, "xg_per_game": 1.7, "npxg_per_game": 1.7, "shots_per_game": 15.1, "shots_on_target_per_game": 5.8, "shots_in_box_per_game": 9.8, "big_chances_per_game": 3.0, "conversion_rate": 12.7, "counter_goals_pct": 18, "set_piece_goals_pct": 24, "corners_per_game": 7.1, "cross_accuracy_pct": 35, "key_passes_per_game": 4.5, "possession_pct": 59.2, "pass_accuracy_pct": 90.1}, "defense": {"goals_against_per_game": 0.63, "xga_per_game": 0.65, "clean_sheet_pct": 44, "shots_against_per_game": 9.2, "sot_against_per_game": 3.4, "tackle_success_pct": 68, "interceptions_per_game": 7.2, "clearances_per_game": 13.5, "aerial_success_pct": 58, "gk_save_pct": 70.2, "gk_psxg_ga": 0.04}, "advanced": {"ppda": 9.1, "field_tilt": 60.2, "deep_completion_per_game": 6.2, "progressive_passes": 68.9, "progressive_carries": 33.2, "shot_creating_actions": 21.4, "goal_creating_actions": 3.4, "xpts_per_game": 1.98}, "tactics": {"primary_formation": "4-2-3-1", "secondary_formation": "4-3-3", "possession_style": true, "high_press": false, "press_intensity": 6.5, "defensive_line": "medium", "wide_play_pct": 52, "set_piece_quality": 7.5, "tactical_flexibility": 7.5}, "key_players": [{"name": "Vinicius Jr.", "position": "FWD", "club": "Real Madrid", "age": 25, "market_value_m": 200, "goals_season": 28, "assists_season": 14, "form_rating": 9.2, "is_injured": false, "is_suspended": false, "injury_detail": ""}, {"name": "Rodrygo", "position": "FWD", "club": "Real Madrid", "age": 23, "market_value_m": 110, "goals_season": 18, "assists_season": 10, "form_rating": 8.4, "is_injured": false, "is_suspended": false, "injury_detail": ""}, {"name": "Bruno Guimarães", "position": "MID", "club": "Newcastle", "age": 27, "market_value_m": 85, "goals_season": 7, "assists_season": 9, "form_rating": 8.5, "is_injured": false, "is_suspended": false, "injury_detail": ""}, {"name": "Endrick", "position": "FWD", "club": "Real Madrid", "age": 18, "market_value_m": 60, "goals_season": 12, "assists_season": 4, "form_rating": 8.0, "is_injured": false, "is_suspended": false, "injury_detail": ""}, {"name": "Ederson", "position": "GK", "club": "Man City", "age": 31, "market_value_m": 40, "goals_season": 0, "assists_season": 0, "form_rating": 8.2, "is_injured": false, "is_suspended": false, "injury_detail": ""}], "injured_players": [{"name": "Neymar Jr.", "position": "FWD", "detail": "ACL recovery – doubtful"}], "suspended_players": [], "recent_form": ["W", "W", "W", "D", "W", "W", "W", "W", "W", "W"], "form_pts_5": 3.0, "form_pts_10": 2.8, "win_rate_10": 90.0, "goals_scored_10": 2.4, "goals_conceded_10": 0.6}, "result": {"p_home": 18.8, "p_draw": 26.8, "p_away": 54.4, "lambda_home": 1.01, "lambda_away": 1.75, "btts_yes": 54.8, "btts_no": 45.2, "score_matrix": [[5.26, 9.58, 9.66, 6.55, 3.4, 1.45], [4.86, 9.9, 9.63, 6.6, 3.41, 1.44], [2.57, 4.94, 4.89, 3.31, 1.73, 0.73], [0.88, 1.68, 1.65, 1.12, 0.6, 0.25], [0.23, 0.43, 0.43, 0.29, 0.15, 0.06], [0.05, 0.09, 0.09, 0.06, 0.03, 0.01]], "top10": [{"home": 1, "away": 1, "prob": 9.9, "type": "draw"}, {"home": 0, "away": 2, "prob": 9.66, "type": "away"}, {"home": 1, "away": 2, "prob": 9.63, "type": "away"}, {"home": 0, "away": 1, "prob": 9.58, "type": "away"}, {"home": 1, "away": 3, "prob": 6.6, "type": "away"}, {"home": 0, "away": 3, "prob": 6.55, "type": "away"}, {"home": 0, "away": 0, "prob": 5.26, "type": "draw"}, {"home": 2, "away": 1, "prob": 4.94, "type": "home"}, {"home": 2, "away": 2, "prob": 4.89, "type": "draw"}, {"home": 1, "away": 0, "prob": 4.86, "type": "home"}], "goal_dist": [{"label": "0", "prob": 5.26}, {"label": "1", "prob": 14.44}, {"label": "2", "prob": 22.13}, {"label": "3", "prob": 21.99}, {"label": "4", "prob": 16.8}, {"label": "5", "prob": 10.29}, {"label": "6+", "prob": 9.08}], "cold": [{"home": 1, "away": 3, "prob": 6.6, "odds": 15.2}, {"home": 2, "away": 2, "prob": 4.89, "odds": 20.5}, {"home": 1, "away": 4, "prob": 3.41, "odds": 29.4}], "models": [{"name": "ELO", "p_home": 11.9, "p_draw": 26.2, "p_away": 61.9, "lam_home": 1.05, "lam_away": 1.46}, {"name": "Poisson", "p_home": 16.2, "p_draw": 19.4, "p_away": 64.4, "lam_home": 1.01, "lam_away": 2.2}, {"name": "Dixon-Coles", "p_home": 15.9, "p_draw": 20.1, "p_away": 64.0, "lam_home": 1.01, "lam_away": 2.2}, {"name": "xG Model", "p_home": 11.1, "p_draw": 20.7, "p_away": 68.2, "lam_home": 0.67, "lam_away": 1.99}, {"name": "Market", "p_home": 40.7, "p_draw": 27.0, "p_away": 32.3, "lam_home": 1.36, "lam_away": 1.2}, {"name": "Monte Carlo", "p_home": 22.1, "p_draw": 23.2, "p_away": 54.7, "lam_home": 1.01, "lam_away": 1.75}], "betting": {"home": {"odds": 2.61, "implied": 38.3, "model": 18.8, "edge": -19.6}, "draw": {"odds": 3.99, "implied": 25.1, "model": 26.8, "edge": 1.8}, "away": {"odds": 3.32, "implied": 30.1, "model": 54.4, "edge": 24.3}, "over": {"line": 2.5, "odds": 1.74, "implied": 57.5, "model": 58.2, "edge": 0.7}, "under": {"line": 2.5, "odds": 2.06, "implied": 48.5, "model": 41.8, "edge": -6.7}, "ah_line": 1.0, "ah_home_odds": 1.91, "ah_away_odds": 2.01, "btts": {"yes": 54.8, "no": 45.2}, "movement": {"open_home": null, "open_draw": null, "open_away": null, "home_drift": null, "away_drift": null, "ah_open": null, "ah_close": null, "ah_move": null, "sharp_index": 0.5, "signal": "neutral", "steam": false}}}, "conf_level": 7, "conf_label": "中高信心", "match": {"date": "2026-06-14", "venue": "MetLife Stadium, East Rutherford, NJ", "comp": "FIFA World Cup 2026", "stage": "Group Stage"}}