{"generated_at": "2026-07-09T14:16:36Z", "home": {"name": "卡達", "short_name": "卡達", "code": "QAT", "confederation": "AFC", "fifa_ranking": 35, "elo_rating": 1570, "spi_rating": 61.0, "squad_value_m": 45, "avg_age": 27.0, "squad_depth": 5.0, "bench_quality": 4.5, "wc_titles": 0, "wc_best_result": "Group Stage", "wc_appearances": 2, "coach": "Marquez Lopez", "coach_rating": 6.5, "attack": {"goals_per_game": 0.77, "xg_per_game": 0.74, "npxg_per_game": 0.831, "shots_per_game": 8.73, "shots_on_target_per_game": 3.154, "shots_in_box_per_game": 5.557, "big_chances_per_game": 1.182, "conversion_rate": 9.6, "counter_goals_pct": 33.46, "set_piece_goals_pct": 19.34, "corners_per_game": 4.489, "cross_accuracy_pct": 25.298, "key_passes_per_game": 2.58, "possession_pct": 48.125, "pass_accuracy_pct": 79.624}, "defense": {"goals_against_per_game": 2.23, "xga_per_game": 2.3, "clean_sheet_pct": 19.617, "shots_against_per_game": 14.052, "sot_against_per_game": 5.298, "tackle_success_pct": 62.129, "interceptions_per_game": 6.208, "clearances_per_game": 15.011, "aerial_success_pct": 53.618, "gk_save_pct": 70.702, "gk_psxg_ga": 0.0}, "advanced": {"ppda": 12.684, "field_tilt": 42.201, "deep_completion_per_game": 3.142, "progressive_passes": 41.785, "progressive_carries": 16.843, "shot_creating_actions": 10.799, "goal_creating_actions": 1.638, "xpts_per_game": 1.156}, "tactics": {"primary_formation": "4-3-3", "secondary_formation": "4-2-3-1", "possession_style": true, "high_press": false, "press_intensity": 5.5, "defensive_line": "medium", "wide_play_pct": 50.88, "set_piece_quality": 5.8, "tactical_flexibility": 5.8}, "key_players": [{"name": "Akram Afif", "position": "FWD", "club": "Al-Sadd", "age": 28, "market_value_m": 6, "goals_season": 12, "assists_season": 8, "form_rating": 8.2, "is_injured": false, "is_suspended": false, "injury_detail": ""}, {"name": "Almoez Ali", "position": "FWD", "club": "Al-Duhail", "age": 28, "market_value_m": 5, "goals_season": 10, "assists_season": 5, "form_rating": 7.8, "is_injured": false, "is_suspended": false, "injury_detail": ""}, {"name": "Hassan Al-Haydos", "position": "MID", "club": "Al-Sadd", "age": 33, "market_value_m": 3, "goals_season": 5, "assists_season": 6, "form_rating": 7.5, "is_injured": false, "is_suspended": false, "injury_detail": ""}, {"name": "Bassam Al-Rawi", "position": "DEF", "club": "Al-Rayyan", "age": 29, "market_value_m": 3, "goals_season": 1, "assists_season": 2, "form_rating": 7.2, "is_injured": false, "is_suspended": false, "injury_detail": ""}], "injured_players": [], "suspended_players": [], "recent_form": [], "form_pts_5": 1.5, "form_pts_10": 1.5, "win_rate_10": 33.0, "goals_scored_10": 0.77, "goals_conceded_10": 2.23}, "away": {"name": "象牙海岸", "short_name": "象牙海岸", "code": "CIV", "confederation": "CAF", "fifa_ranking": 43, "elo_rating": 1815, "spi_rating": 67.5, "squad_value_m": 280, "avg_age": 27.8, "squad_depth": 5.8, "bench_quality": 5.4, "wc_titles": 0, "wc_best_result": "Quarter-Final", "wc_appearances": 9, "coach": "Emerse Fae", "coach_rating": 7.0, "attack": {"goals_per_game": 1.11, "xg_per_game": 1.06, "npxg_per_game": 1.059, "shots_per_game": 10.275, "shots_on_target_per_game": 3.597, "shots_in_box_per_game": 6.088, "big_chances_per_game": 1.491, "conversion_rate": 10.6, "counter_goals_pct": 33.67, "set_piece_goals_pct": 28.31, "corners_per_game": 5.048, "cross_accuracy_pct": 28.063, "key_passes_per_game": 2.999, "possession_pct": 50.963, "pass_accuracy_pct": 77.983}, "defense": {"goals_against_per_game": 1.25, "xga_per_game": 1.29, "clean_sheet_pct": 26.642, "shots_against_per_game": 13.009, "sot_against_per_game": 4.858, "tackle_success_pct": 64.6, "interceptions_per_game": 6.864, "clearances_per_game": 15.621, "aerial_success_pct": 54.46, "gk_save_pct": 72.619, "gk_psxg_ga": 0.043}, "advanced": {"ppda": 11.849, "field_tilt": 46.81, "deep_completion_per_game": 3.828, "progressive_passes": 47.692, "progressive_carries": 20.313, "shot_creating_actions": 12.53, "goal_creating_actions": 1.943, "xpts_per_game": 1.432}, "tactics": {"primary_formation": "4-3-3", "secondary_formation": "4-2-3-1", "possession_style": true, "high_press": true, "press_intensity": 6.3, "defensive_line": "medium", "wide_play_pct": 44.36, "set_piece_quality": 6.5, "tactical_flexibility": 6.5}, "key_players": [{"name": "Sebastien Haller", "position": "FWD", "club": "Dortmund", "age": 30, "market_value_m": 22, "goals_season": 10, "assists_season": 4, "form_rating": 7.8, "is_injured": false, "is_suspended": false, "injury_detail": ""}, {"name": "Franck Kessie", "position": "MID", "club": "Al-Ahli", "age": 27, "market_value_m": 18, "goals_season": 5, "assists_season": 7, "form_rating": 7.8, "is_injured": false, "is_suspended": false, "injury_detail": ""}, {"name": "Simon Adingra", "position": "FWD", "club": "Brighton", "age": 22, "market_value_m": 30, "goals_season": 8, "assists_season": 6, "form_rating": 8.2, "is_injured": false, "is_suspended": false, "injury_detail": ""}, {"name": "Serge Aurier", "position": "DEF", "club": "Nottm Forest", "age": 32, "market_value_m": 8, "goals_season": 2, "assists_season": 4, "form_rating": 7.4, "is_injured": false, "is_suspended": false, "injury_detail": ""}], "injured_players": [], "suspended_players": [], "recent_form": [], "form_pts_5": 1.5, "form_pts_10": 1.5, "win_rate_10": 33.0, "goals_scored_10": 1.11, "goals_conceded_10": 1.25}, "result": {"p_home": 20.7, "p_draw": 28.8, "p_away": 50.5, "lambda_home": 0.82, "lambda_away": 1.63, "btts_yes": 44.3, "btts_no": 55.7, "score_matrix": [[8.22, 13.65, 12.31, 7.41, 3.39, 1.25], [5.84, 10.75, 9.31, 5.58, 2.54, 0.94], [2.35, 4.03, 3.55, 2.12, 0.97, 0.35], [0.62, 1.06, 0.92, 0.55, 0.25, 0.09], [0.12, 0.21, 0.19, 0.11, 0.05, 0.02], [0.02, 0.04, 0.03, 0.02, 0.01, 0.0]], "top10": [{"home": 0, "away": 1, "prob": 13.65, "type": "away"}, {"home": 0, "away": 2, "prob": 12.31, "type": "away"}, {"home": 1, "away": 1, "prob": 10.75, "type": "draw"}, {"home": 1, "away": 2, "prob": 9.31, "type": "away"}, {"home": 0, "away": 0, "prob": 8.22, "type": "draw"}, {"home": 0, "away": 3, "prob": 7.41, "type": "away"}, {"home": 1, "away": 0, "prob": 5.84, "type": "home"}, {"home": 1, "away": 3, "prob": 5.58, "type": "away"}, {"home": 2, "away": 1, "prob": 4.03, "type": "home"}, {"home": 2, "away": 2, "prob": 3.55, "type": "draw"}], "goal_dist": [{"label": "0", "prob": 8.22}, {"label": "1", "prob": 19.49}, {"label": "2", "prob": 25.41}, {"label": "3", "prob": 21.37}, {"label": "4", "prob": 13.7}, {"label": "5", "prob": 7.07}, {"label": "6+", "prob": 4.73}], "cold": [{"home": 1, "away": 3, "prob": 5.58, "odds": 17.9}, {"home": 2, "away": 2, "prob": 3.55, "odds": 28.2}, {"home": 0, "away": 4, "prob": 3.39, "odds": 29.5}], "models": [{"name": "ELO", "p_home": 21.0, "p_draw": 27.1, "p_away": 51.9, "lam_home": 1.2, "lam_away": 1.29}, {"name": "Poisson", "p_home": 13.6, "p_draw": 21.3, "p_away": 65.1, "lam_home": 0.73, "lam_away": 1.9}, {"name": "Dixon-Coles", "p_home": 13.2, "p_draw": 22.1, "p_away": 64.7, "lam_home": 0.73, "lam_away": 1.9}, {"name": "xG Model", "p_home": 17.4, "p_draw": 25.0, "p_away": 57.6, "lam_home": 0.81, "lam_away": 1.67}, {"name": "Market", "p_home": 40.1, "p_draw": 27.2, "p_away": 32.7, "lam_home": 1.34, "lam_away": 1.2}, {"name": "ML", "p_home": 8.7, "p_draw": 9.4, "p_away": 81.9, "lam_home": 0.3, "lam_away": 2.44}, {"name": "Monte Carlo", "p_home": 19.1, "p_draw": 24.7, "p_away": 56.2, "lam_home": 0.82, "lam_away": 1.63}], "betting": {"home": {"odds": 2.65, "implied": 37.7, "model": 20.7, "edge": -17.0}, "draw": {"odds": 3.97, "implied": 25.2, "model": 28.8, "edge": 3.6}, "away": {"odds": 3.27, "implied": 30.6, "model": 50.5, "edge": 19.9}, "over": {"line": 2.5, "odds": 1.74, "implied": 57.5, "model": 46.9, "edge": -10.6}, "under": {"line": 2.5, "odds": 2.06, "implied": 48.5, "model": 53.1, "edge": 4.6}, "ah_line": 1.0, "ah_home_odds": 1.91, "ah_away_odds": 2.02, "btts": {"yes": 44.3, "no": 55.7}, "movement": {"open_home": null, "open_draw": null, "open_away": null, "home_drift": null, "away_drift": null, "ah_open": null, "ah_close": null, "ah_move": null, "sharp_index": 0.5, "signal": "neutral", "steam": false}}}, "conf_level": 7, "conf_label": "中高信心", "match": {"date": "2026-06-14", "venue": "MetLife Stadium, East Rutherford, NJ", "comp": "FIFA World Cup 2026", "stage": "Group Stage"}}